nsforest/__init__.py
nsforest/__main__.py
nsforest/evaluating/__init__.py
nsforest/evaluating/_run_markers.py
nsforest/nsforesting/__init__.py
nsforest/nsforesting/_run_nsf.py
nsforest/nsforesting/calculate_fraction.py
nsforest/nsforesting/mydecisiontreeevaluation.py
nsforest/nsforesting/myrandomforest.py
nsforest/plotting/__init__.py
nsforest/plotting/_make_plots.py
nsforest/preprocessing/__init__.py
nsforest/preprocessing/_add_ann.py
nsforest/utils.py
nsforest-4.1.dist-info/LICENSE
nsforest-4.1.dist-info/METADATA
nsforest-4.1.dist-info/WHEEL
nsforest-4.1.dist-info/RECORD
