Metadata-Version: 2.3
Name: nsforest
Version: 4.1
Summary: A machine learning method for the discovery of minimum marker gene combinations for cell type identification from single-cell RNA sequencing
License: MIT
Author: Renee Zhang
Author-email: yun.zhang@nih.gov
Maintainer: Beverly Peng
Maintainer-email: bpeng@jcvi.org
Requires-Python: >=3.8,<4.0
Classifier: License :: OSI Approved :: MIT License
Classifier: Programming Language :: Python :: 3
Classifier: Programming Language :: Python :: 3.8
Classifier: Programming Language :: Python :: 3.9
Classifier: Programming Language :: Python :: 3.10
Classifier: Programming Language :: Python :: 3.11
Classifier: Programming Language :: Python :: 3.12
Classifier: Programming Language :: Python :: 3.13
Requires-Dist: scanpy (>=1.9.3,<2.0.0)
